LICENSE
MANIFEST.in
README.md
setup.cfg
setup.py
certbot_dns_selectel_v2/__init__.py
certbot_dns_selectel_v2/dns_selectel.py
certbot_dns_selectel_v2/dns_selectel_test.py
certbot_dns_selectel_v2.egg-info/PKG-INFO
certbot_dns_selectel_v2.egg-info/SOURCES.txt
certbot_dns_selectel_v2.egg-info/dependency_links.txt
certbot_dns_selectel_v2.egg-info/entry_points.txt
certbot_dns_selectel_v2.egg-info/requires.txt
certbot_dns_selectel_v2.egg-info/top_level.txt
docs/Makefile
docs/api.rst
docs/conf.py
docs/index.rst
docs/make.bat
docs/api/dns_selectel.rst